thyme/__init__.py
thyme/grid/__init__.py
thyme/grid/regulargrid.py
thyme/model/__init__.py
thyme/model/fvcom.py
thyme/model/hycom.py
thyme/model/model.py
thyme/model/pom.py
thyme/model/rectilinear.py
thyme/model/roms.py
thyme/util/__init__.py
thyme/util/dateutil.py
thyme/util/interp.py
thyme-0.3.4.dist-info/LICENSE
thyme-0.3.4.dist-info/METADATA
thyme-0.3.4.dist-info/WHEEL
thyme-0.3.4.dist-info/top_level.txt
thyme-0.3.4.dist-info/RECORD
