Metadata-Version: 2.1
Name: thyme
Version: 0.3.4
Summary: Tools for Hydrodynamic Model Output Extraction and Processing
Home-page: https://github.com/noaa-ocs-modeling/thyme
Author: Erin Nagel, Jason Greenlaw
Author-email: erin.nagel@noaa.gov, jason.greenlaw@noaa.gov
License: BSD-2-Clause
Platform: UNKNOWN
Classifier: Programming Language :: Python :: 3
Classifier: Intended Audience :: Science/Research
Classifier: License :: OSI Approved :: BSD License
Classifier: Operating System :: OS Independent
Requires-Dist: shapely
Requires-Dist: numpy
Requires-Dist: scipy
Requires-Dist: netCDF4
Requires-Dist: gdal
